shx/__init__.py
shx/shx.py
shx/test_shx.py
shx-0.4.2.dist-info/LICENSE
shx-0.4.2.dist-info/METADATA
shx-0.4.2.dist-info/WHEEL
shx-0.4.2.dist-info/entry_points.txt
shx-0.4.2.dist-info/top_level.txt
shx-0.4.2.dist-info/RECORD
